jarviscloud/__init__.py
jarviscloud/jarviscloud.py
jarviscloud-0.1.dist-info/METADATA
jarviscloud-0.1.dist-info/WHEEL
jarviscloud-0.1.dist-info/top_level.txt
jarviscloud-0.1.dist-info/RECORD
