Metadata-Version: 2.1
Name: jarviscloud
Version: 0.1
Summary: Testing installation of Package
Home-page: https://github.com/selvakumar-sss/jarvis_pause.git
Author: selvakumar
Author-email: eyesway@gmail.com
License: MIT
Platform: UNKNOWN
